resizewin.py
resizewin-0.1.1.dist-info/entry_points.txt
resizewin-0.1.1.dist-info/WHEEL
resizewin-0.1.1.dist-info/METADATA
resizewin-0.1.1.dist-info/RECORD
