Metadata-Version: 2.1
Name: resizewin
Version: 0.1.1
Summary: `resizewin` detects the terminal size.
Author-email: Eugene Kim <ek@karma3labs.com>
Requires-Python: >=3.8
Classifier: License :: OSI Approved :: MIT License
Project-URL: Source, https://github.com/Karma3Labs/resizewin
